create_uv_project/__init__.py
create_uv_project/app.py
create_uv_project-0.1.0.dist-info/METADATA
create_uv_project-0.1.0.dist-info/WHEEL
create_uv_project-0.1.0.dist-info/entry_points.txt
create_uv_project-0.1.0.dist-info/RECORD
