Metadata-Version: 2.4
Name: create-uv-project
Version: 0.1.0
Summary: A modern Python project scaffolder powered by UV.
Author-email: hupanpan <angrypandahu@163.com>
Requires-Python: >=3.12
Requires-Dist: jinja2>=3.0.0
Requires-Dist: uv
